letbabytalk/__init__.py
letbabytalk/audio_to_tensor.py
letbabytalk/train.py
letbabytalk/trainer.py
letbabytalk/utils.py
letbabytalk/backend_inference/__init__.py
letbabytalk/backend_inference/inference.py
letbabytalk/backend_inference/model.py
letbabytalk/data/BabyChillanto.py
letbabytalk/data/DataCleaner.py
letbabytalk/data/DonateACry.py
letbabytalk/data/Mix.py
letbabytalk/data/PreClassify.py
letbabytalk/data/__init__.py
letbabytalk/loss/__init__.py
letbabytalk/loss/cross_entropy_loss.py
letbabytalk/loss/supervised_contrastive_loss.py
letbabytalk/models/PreClassify.py
letbabytalk/models/Transformer_model.py
letbabytalk/models/__init__.py
letbabytalk/models/conv_mlp.py
letbabytalk/models/melgan.py
letbabytalk/models/mlp.py
letbabytalk/models/mlp_attention.py
letbabytalk/models/onedcnn.py
letbabytalk/models/resnet.py
letbabytalk/predetect/__init__.py
letbabytalk/predetect/main.py
letbabytalk-0.1.3.dist-info/METADATA
letbabytalk-0.1.3.dist-info/WHEEL
letbabytalk-0.1.3.dist-info/top_level.txt
letbabytalk-0.1.3.dist-info/RECORD
