Metadata-Version: 2.1
Name: letbabytalk
Version: 0.1.3
Summary: letbabytalk
Author: Minghao Fu
Author-email: isminghaofu@gmail.com
License: MIT
Classifier: Programming Language :: Python :: 3
Classifier: License :: OSI Approved :: MIT License
Classifier: Operating System :: OS Independent
Requires-Python: >=3.6
